[{
        "gender": "M",
        "givenName": "Peter",
        "familyName": "Rees",
        "birthDate": "1992-10-29T08:32:00.000Z",
        "jobTitle": "Information Technology Specialist",
        "address": {
            "contactType": "primary",
            "streetAddress": "20 Route 4",
            "addressLocality": "Salford, Greater Manchester",
            "postalCode": "M41 8ZE",
            "addressCountry": "UK",
            "telephone": "(0516 73) 3611"
        },
        "description": "Peter Rees",
        "email": "peter.rees@example.com"
    }]